{
    "kite.showWelcomeNotificationOnStartup": false,
    "editor.suggestSelection": "first",
    "vsintellicode.modify.editor.suggestSelection": "automaticallyOverrodeDefaultValue",
    "tabnine.experimentalAutoImports": true,
    "python.pythonPath": "c:\\program files\\blender foundation\\blender\\2.80\\python\\python.exe",
    "python.analysis.autoImportCompletions": true,
    "python.analysis.completeFunctionParens": true,
    "python.autoComplete.addBrackets": true,
    "python-coding-tools.update-module-variable.enableOnSave": true,
    "python-coding-tools.update-module-variable.variableName": "__updated__",
    "python.analysis.information": ["editor.suggestSelection"],
    "python.analysis.typeCheckingMode": "basic",
    "python.disableInstallationCheck":false,
    "python.autoUpdateLanguageServer": true,
    "python.experiments.enabled": true,
    "pythonIndent.useTabOnHangingIndent":true,
    "python.terminal.activateEnvironment": true,
    "python.insidersChannel":"weekly",
    "python.formatting.autopep8Args": ["--max-line-length", "120", "--experimental"],
    "python.formatting.blackArgs": ["--line-length", "100"],
    "python.linting.flake8Enabled": true,
    "python.linting.flake8Args": ["--ignore=E24,W504,E201,E202,E226,E231,E302,E501", "--verbose"],
    "python.linting.pylintEnabled": false,
    "python.linting.pydocstyleEnabled": false,
    "python.linting.pylintArgs": ["--reports", "12", "--disable", "I0011"],
    "python.linting.enabled": true,
    "python.linting.lintOnSave": true,
    "files.autoSave": "onFocusChange",
    "editor.defaultFormatter": "TabNine.tabnine-vscode",
    "sourcery.token": "user__H9qpawoUM5BYpkzbG6_7QpS0OBgRYQS2eFDUKrQPSZks4rwyCCP_hX2F0s",
    "AREPL.defaultImports": [
        "import sys",
        "from arepl_dump import dump",
        "import tkinter as tk",
        "import tkinter.ttk as ttk",
        "import _support"
    ],
    "python.languageServer": "Pylance",
    "typescript.suggest.paths": false,
    "files.associations": {
        ".tcl": "TCL8.6",
        ".py": "Python3.7"
    },
    "editor.codeActionsOnSave": {"source.fixAll": true, "source.organizeImports": true,
        "source.reports": true
    },
    "files.exclude": {
        "**/.git": false
    },
    "editor.fontFamily": "'Verdana', 'MS Comic Sans'",
    "editor.fontWeight": "bold",
    "files.defaultLanguage": "${activeEditorLanguage}",
    "workbench.colorTheme": "Solarized Dark",
    "workbench.settings.openDefaultKeybindings": true,
    "workbench.settings.openDefaultSettings": true,
    "window.restoreFullscreen": true,
    "window.openFoldersInNewWindow": "on",
    "search.smartCase": true,
    "debug.allowBreakpointsEverywhere": true,
    "debug.console.closeOnEnd": true,
    "scm.alwaysShowActions": true,
    "terminal.integrated.automationShell.linux": "on",
    "AREPL.pyGuiLibraries": [
        "matplotlib",
        "tkinter",
        "kivy",
        "pyforms",
        "PyQt4",
        "PyQt5",
        "wx",
        "pyside",
        "plotly",
        "ggplot",
        "bokeh",
        "ppb",
        "PySimpleGUI",
        "pyglet",
        "open3d",
        "panda3d-kivy",
        "dearpygui",
        "pi3d",
        "panda3d",
        "bpy-build",
        "bpy"
    ],
    "code-runner.executorMap": {
      "javascript": "node",
      "python": "python -u",
      "dart": "dart"
    },
      "indentRainbow.includedLanguages": ["python"],
      "indentRainbow.ignoreErrorLanguages" : [
    "markdown",
    "haskell"
  ],
      "indentRainbow.colors": [
        "rgba(255,255,64,0.07)",
        "rgba(127,255,127,0.07)",
        "rgba(255,127,255,0.07)",
        "rgba(79,236,236,0.07)"
      ],
    "editor.semanticTokenColorCustomizations": {
        "[One Dark Pro]": {
            "enabled": true,
            "rules": {
                "magicFunction:python": "#ee0000",
                "function.declaration:python": "#990000",
                "*.decorator:python": "#0000dd",
                "*.typeHint:python": "#5500aa",
                "*.typeHintComment:python": "#aaaaaa"
            }
        }
    },
    "bracket-pair-colorizer-2.forceUniqueOpeningColor": true,
    "sync.autoUpload": true,
    "sync.autoDownload": true,
    "codetogether.userName": "maheshcdac",
    "css.trace.server": "messages",
    "git.allowForcePush": true,
    "git.autofetch": true,
    "git.fetchOnPull": true,
    "git.path": "C:/Program Files/Git/bin/git.exe",
    "gitlens.advanced.messages": {
        "suppressCommitHasNoPreviousCommitWarning": true,
        "suppressCommitNotFoundWarning": false,
        "suppressFileNotUnderSourceControlWarning": false,
        "suppressGitDisabledWarning": false,
        "suppressGitVersionWarning": false,
        "suppressLineUncommittedWarning": false,
        "suppressNoRepositoryWarning": false
    },
    "html.format.indentInnerHtml": true,
    "pylance.insidersChannel": "daily",
    "terminal.external.windowsExec": "C:\\Program Files\\PowerShell\\7",
    "code-runner.runInTerminal": true,
    "python.terminal.activateEnvInCurrentTerminal": true,
    "npm-intellisense.scanDevDependencies": true,
    "path-intellisense.autoSlashAfterDirectory": true,
    "path-intellisense.showHiddenFiles": true,
    "python.venvPath": "C:\\Program Files\\Blender Foundation\\Blender\\2.80\\python\\lib\\venv",
    "python.autoComplete.extraPaths": [
        "**/site-packages/**"
    ],
    "python.testing.pytestEnabled": true,
    "code-runner.clearPreviousOutput": true,
    "code-runner.defaultLanguage": "python",
    "vsintellicode.features.python.deepLearning": "enabled",
    "liveshare.allowGuestDebugControl": true,
    "liveshare.allowInvites": "all",
    "yaml.trace.server": "messages",
    "python.analysis.extraPaths": [],
    "terminal.integrated.automationShell.osx": "true",
    "npm-intellisense.packageSubfoldersIntellisense": true,
    "npm-intellisense.showBuildInLibs": true,
    "editor.tabSize": 2,
    "pasteAndIndent.selectAfter": true,
    "prettier.useTabs": true,
    "sync.gist": "vscode://vscode.github-authentication/did-authenticate?windowid=1&code=ec04a8ff411b7a85ebba&state=1908b67b-9ec3-4ad6-be0a-c7bc342ad005",
    "git.allowNoVerifyCommit": true,
    "git.enableSmartCommit": true,
    "remote.SSH.showLoginTerminal": true,
    "code-runner.saveFileBeforeRun": true,
    "code-runner.saveAllFilesBeforeRun": true,
    "pythonPreview.heapObject.fontSize": 12,
    "pythonPreview.fontSize": 12,
    "todo-tree.tree.showScanModeButton": false,
    "[dart]": {
        "editor.formatOnSave": true,
        "editor.formatOnType": true,
        "editor.rulers": [
            80
        ],
        "editor.selectionHighlight": false,
        "editor.suggest.snippetsPreventQuickSuggestions": false,
        "editor.suggestSelection": "first",
        "editor.tabCompletion": "onlySnippets",
        "editor.wordBasedSuggestions": false
    },
    "enableTelemetry": true,
    "blender.executables": [
        {
            "path": "c:\\Program Files\\Blender Foundation\\Blender 2.90\\blender.exe",
            "name": "BL2.9",
            "isDebug": false
        },
        {
            "path": "c:\\Program Files\\Blender Foundation\\Blender\\blender.exe",
            "name": "BL2.8",
            "isDebug": true
        }
    ],
    "[python]": {
        "editor.wordBasedSuggestions": false
    },
    "pythonPreview.codeFooterDocs.fontFamily": "verdana, arial, helvetica, sans",
    "python.linter": "autopep8",
    "editor.tabCompletion": "on",
    "editor.wrappingStrategy": "advanced",
    "editor.formatOnPaste": true,
    "editor.formatOnSave": true,
    "editor.formatOnType": true,
    "editor.formatOnSaveMode": "modifications",
    "workbench.commandPalette.preserveInput": true,
    "workbench.preferredHighContrastColorTheme": "Red",
    "workbench.preferredLightColorTheme": "Default Dark+",
    "scm.alwaysShowRepositories": true,
    "blender.allowModifyExternalPython": true,
    "remote.downloadExtensionsLocally": true,
    "AREPL.pythonPath": "C:\\Program Files\\Blender Foundation\\Blender\\2.80\\python\\python.exe",
    "blender.addon.reloadOnSave": true,
    "bracketPairColorizer.consecutivePairColors": [

        "()",
        "[]",
        "{}",
        [
            "Gold",
            "Orchid",
            "LightSkyBlue"
        ],
        "Red"
    ],
    "git.confirmSync": false,
    "git.ignoredRepositories": [
        "templates"
    ],
    "autoInstall.secure": false,
    "autoInstall.startOnLaunch": true,
    "python.defaultInterpreterPath": "C:\\Program Files\\Blender Foundation\\Blender\\2.80\\python\\python.exe",
    "autoAlign.enabled": {
      "csv": true,
      "bsv": true
    },
    "testExplorer.onStart":"reset",
    "testExplorer.addToEditorContextMenu": true,
    "testExplorer.onReload": "reset",
    "testExplorer.showOnRun": true,
    "testExplorer.sort": "byLabelWithSuitesFirst"
}